azcam/__init__.py
azcam/api.py
azcam/cli.py
azcam/cmdserver.py
azcam/database.py
azcam/database_server.py
azcam/exceptions.py
azcam/fits.py
azcam/header.py
azcam/image.py
azcam/image_focalplane.py
azcam/image_headers.py
azcam/image_io.py
azcam/logger.py
azcam/parameters.py
azcam/parameters_server.py
azcam/remote_logger.py
azcam/server.py
azcam/shortcuts.py
azcam/sockets.py
azcam/utils.py
azcam/scripts/__init__.py
azcam/scripts/scripts.py
azcam/scripts/test_arc_controller.py
azcam/scripts/test_instrument.py
azcam/scripts/test_mag_controller.py
azcam/scripts/test_server.py
azcam/tools/__init__.py
azcam/tools/controller.py
azcam/tools/display.py
azcam/tools/ds9display.py
azcam/tools/exposure.py
azcam/tools/exposure_filename.py
azcam/tools/exposure_obstime.py
azcam/tools/exposure_sendimage.py
azcam/tools/focus.py
azcam/tools/instrument.py
azcam/tools/telescope.py
azcam/tools/tempcon.py
azcam/tools/tempcon_cryocon24.py
azcam/tools/tools.py
azcam/tools/arc/__init__.py
azcam/tools/arc/camera_server.py
azcam/tools/arc/controller_arc.py
azcam/tools/arc/exposure_arc.py
azcam/tools/arc/receive_data.py
azcam/tools/arc/tempcon_arc.py
azcam/tools/archon/__init__.py
azcam/tools/archon/controller_archon.py
azcam/tools/archon/exposure_archon.py
azcam/tools/archon/tempcon_archon.py
azcam/tools/ascom/__init__.py
azcam/tools/ascom/controller_ascom.py
azcam/tools/ascom/exposure_ascom.py
azcam/tools/ascom/tempcon_ascom.py
azcam/tools/mag/__init__.py
azcam/tools/mag/camera_server.py
azcam/tools/mag/controller_mag.py
azcam/tools/mag/exposure_mag.py
azcam/tools/mag/receive_data.py
azcam/tools/mag/tempcon_mag.py
azcam/tools/mag/udpinterface.py
azcam/web/__init__.py
azcam/web/fastapi_server.py
azcam/web/favicon.ico
azcam/web/index.html
azcam/web/style.css
azcam/web/test_api.py
azcam-26.0.3.dist-info/licenses/LICENSE
azcam-26.0.3.dist-info/WHEEL
azcam-26.0.3.dist-info/METADATA
azcam-26.0.3.dist-info/RECORD
