Metadata-Version: 2.4
Name: azcam
Version: 26.0.3
Summary: Acquisition and analysis package for scientific imaging
Keywords: ccd,imaging,astronomy,sensors
Author: Michael Lesser
Author-email: mlesser@arizona.edu
Requires-Python: >= 3.10
License-File: LICENSE
Requires-Dist: loguru
Requires-Dist: numpy
Requires-Dist: astropy
Requires-Dist: psutil
Requires-Dist: fastapi
Requires-Dist: uvicorn
Requires-Dist: jinja2
Project-URL: Documentation, https://azcam.readthedocs.io/
Project-URL: Repository, https://github.com/mplesser/azcam/
